<?xml version="1.0" encoding="UTF-8" standalone="yes" ?>
<musicdescription xmlns="http://www.ircam.fr/musicdescription/1.1" xmlns:xsi="http://www.w3.org/2001/XMLSchema-instance" xsi:schemaLocation="http://www.ircam.fr/musicdescription/1.1 http://recherche.ircam.fr/anasyn/xsd/musicdescription_1.1.xsd" format="20140305A" date="2015-10-28" >
<media>./blues/blues.00052.wav</media>
<descriptiondefinition id="1" >
	<type>beattype</type>
	<generator name="AudioSculpt" version="3.3.9" date="2015-10-28" />
</descriptiondefinition>
<segment time="0.0217694785693241" length="0" sourcetrack="0"  >
	<beattype id="1" pattern="0" measure="0" beat="1" tatum="1" />
</segment>
<segment time="0.949149328985461" length="0" sourcetrack="0"  >
	<beattype id="1" pattern="0" measure="0" beat="1" tatum="1" />
</segment>
<segment time="1.797504" length="0" sourcetrack="0"  >
	<beattype id="1" pattern="0" measure="0" beat="0" tatum="1" />
</segment>
<segment time="2.2393297039" length="0" sourcetrack="0"  >
	<beattype id="1" pattern="0" measure="0" beat="1" tatum="1" />
</segment>
<segment time="3.014235" length="0" sourcetrack="0"  >
	<beattype id="1" pattern="0" measure="0" beat="0" tatum="1" />
</segment>
<segment time="3.41780830982659" length="0" sourcetrack="0"  >
	<beattype id="1" pattern="0" measure="0" beat="1" tatum="1" />
</segment>
<segment time="4.234615" length="0" sourcetrack="0"  >
	<beattype id="1" pattern="0" measure="0" beat="0" tatum="1" />
</segment>
<segment time="4.6600099761" length="0" sourcetrack="0"  >
	<beattype id="1" pattern="0" measure="1" beat="1" tatum="1" />
</segment>
<segment time="5.453957" length="0" sourcetrack="0"  >
	<beattype id="1" pattern="0" measure="0" beat="0" tatum="1" />
</segment>
<segment time="5.8674476178" length="0" sourcetrack="0"  >
	<beattype id="1" pattern="0" measure="0" beat="1" tatum="1" />
</segment>
<segment time="6.661395" length="0" sourcetrack="0"  >
	<beattype id="1" pattern="0" measure="0" beat="0" tatum="1" />
</segment>
<segment time="7.0748852595" length="0" sourcetrack="0"  >
	<beattype id="1" pattern="0" measure="0" beat="1" tatum="1" />
</segment>
<segment time="7.845734" length="0" sourcetrack="0"  >
	<beattype id="1" pattern="0" measure="0" beat="0" tatum="1" />
</segment>
<segment time="8.24719430775518" length="0" sourcetrack="0"  >
	<beattype id="1" pattern="0" measure="0" beat="1" tatum="1" />
</segment>
<segment time="9.045406" length="0" sourcetrack="0"  >
	<beattype id="1" pattern="0" measure="0" beat="0" tatum="1" />
</segment>
<segment time="9.46111693480674" length="0" sourcetrack="0"  >
	<beattype id="1" pattern="0" measure="1" beat="1" tatum="1" />
</segment>
<segment time="10.247408" length="0" sourcetrack="0"  >
	<beattype id="1" pattern="0" measure="0" beat="0" tatum="1" />
</segment>
<segment time="10.6569102400674" length="0" sourcetrack="0"  >
	<beattype id="1" pattern="0" measure="0" beat="1" tatum="1" />
</segment>
<segment time="11.469715" length="0" sourcetrack="0"  >
	<beattype id="1" pattern="0" measure="0" beat="0" tatum="1" />
</segment>
<segment time="11.8930258491" length="0" sourcetrack="0"  >
	<beattype id="1" pattern="0" measure="0" beat="1" tatum="1" />
</segment>
<segment time="12.683156" length="0" sourcetrack="0"  >
	<beattype id="1" pattern="0" measure="0" beat="0" tatum="1" />
</segment>
<segment time="13.0946585021" length="0" sourcetrack="0"  >
	<beattype id="1" pattern="0" measure="0" beat="1" tatum="1" />
</segment>
<segment time="13.899428" length="0" sourcetrack="0"  >
	<beattype id="1" pattern="0" measure="0" beat="0" tatum="1" />
</segment>
<segment time="14.3185547089805" length="0" sourcetrack="0"  >
	<beattype id="1" pattern="0" measure="1" beat="1" tatum="1" />
</segment>
<segment time="15.093099" length="0" sourcetrack="0"  >
	<beattype id="1" pattern="0" measure="0" beat="0" tatum="1" />
</segment>
<segment time="15.4964847406205" length="0" sourcetrack="0"  >
	<beattype id="1" pattern="0" measure="0" beat="1" tatum="1" />
</segment>
<segment time="16.323032" length="0" sourcetrack="0"  >
	<beattype id="1" pattern="0" measure="0" beat="0" tatum="1" />
</segment>
<segment time="16.7535001491611" length="0" sourcetrack="0"  >
	<beattype id="1" pattern="0" measure="0" beat="1" tatum="1" />
</segment>
<segment time="17.492892" length="0" sourcetrack="0"  >
	<beattype id="1" pattern="0" measure="0" beat="0" tatum="1" />
</segment>
<segment time="17.8779691597" length="0" sourcetrack="0"  >
	<beattype id="1" pattern="0" measure="0" beat="1" tatum="1" />
</segment>
<segment time="18.6848" length="0" sourcetrack="0"  >
	<beattype id="1" pattern="0" measure="0" beat="0" tatum="1" />
</segment>
<segment time="19.1050001210225" length="0" sourcetrack="0"  >
	<beattype id="1" pattern="0" measure="1" beat="1" tatum="1" />
</segment>
<segment time="19.880134" length="0" sourcetrack="0"  >
	<beattype id="1" pattern="0" measure="0" beat="0" tatum="1" />
</segment>
<segment time="20.2838256797096" length="0" sourcetrack="0"  >
	<beattype id="1" pattern="0" measure="0" beat="1" tatum="1" />
</segment>
<segment time="21.123329" length="0" sourcetrack="0"  >
	<beattype id="1" pattern="0" measure="0" beat="0" tatum="1" />
</segment>
<segment time="21.5605450339934" length="0" sourcetrack="0"  >
	<beattype id="1" pattern="0" measure="0" beat="1" tatum="1" />
</segment>
<segment time="22.276696" length="0" sourcetrack="0"  >
	<beattype id="1" pattern="0" measure="0" beat="0" tatum="1" />
</segment>
<segment time="22.64966984" length="0" sourcetrack="0"  >
	<beattype id="1" pattern="0" measure="0" beat="1" tatum="1" />
</segment>
<segment time="23.435983" length="0" sourcetrack="0"  >
	<beattype id="1" pattern="0" measure="0" beat="0" tatum="1" />
</segment>
<segment time="23.8454975044" length="0" sourcetrack="0"  >
	<beattype id="1" pattern="0" measure="1" beat="1" tatum="1" />
</segment>
<segment time="24.639445" length="0" sourcetrack="0"  >
	<beattype id="1" pattern="0" measure="0" beat="0" tatum="1" />
</segment>
<segment time="25.0529351461" length="0" sourcetrack="0"  >
	<beattype id="1" pattern="0" measure="0" beat="1" tatum="1" />
</segment>
<segment time="25.876584" length="0" sourcetrack="0"  >
	<beattype id="1" pattern="0" measure="0" beat="0" tatum="1" />
</segment>
<segment time="26.3055426719502" length="0" sourcetrack="0"  >
	<beattype id="1" pattern="0" measure="0" beat="1" tatum="1" />
</segment>
<segment time="27.047904" length="0" sourcetrack="0"  >
	<beattype id="1" pattern="0" measure="0" beat="0" tatum="1" />
</segment>
<segment time="27.4345282303236" length="0" sourcetrack="0"  >
	<beattype id="1" pattern="0" measure="0" beat="1" tatum="1" />
</segment>
<segment time="28.230653" length="0" sourcetrack="0"  >
	<beattype id="1" pattern="0" measure="0" beat="0" tatum="1" />
</segment>
<segment time="28.6452780097885" length="0" sourcetrack="0"  >
	<beattype id="1" pattern="0" measure="1" beat="1" tatum="1" />
</segment>
<segment time="29.426836" length="0" sourcetrack="0"  >
	<beattype id="1" pattern="0" measure="0" beat="0" tatum="1" />
</segment>
<segment time="29.8338737487793" length="0" sourcetrack="0"  >
	<beattype id="1" pattern="0" measure="0" beat="1" tatum="1" />
</segment>
</musicdescription>
