<?xml version="1.0" encoding="UTF-8" standalone="yes" ?>
<musicdescription xmlns="http://www.ircam.fr/musicdescription/1.1" xmlns:xsi="http://www.w3.org/2001/XMLSchema-instance" xsi:schemaLocation="http://www.ircam.fr/musicdescription/1.1 http://recherche.ircam.fr/anasyn/xsd/musicdescription_1.1.xsd" format="20140305A" date="2015-10-28" >
<media>./disco/disco.00053.wav</media>
<descriptiondefinition id="1" >
	<type>beattype</type>
	<generator name="AudioSculpt" version="3.3.9" date="2015-10-28" />
</descriptiondefinition>
<segment time="0.178548753261566" length="0" sourcetrack="0"  >
	<beattype id="1" pattern="0" measure="0" beat="1" tatum="1" />
</segment>
<segment time="0.464938" length="0" sourcetrack="0"  >
	<beattype id="1" pattern="0" measure="0" beat="0" tatum="1" />
</segment>
<segment time="0.6081278899" length="0" sourcetrack="0"  >
	<beattype id="1" pattern="0" measure="0" beat="1" tatum="1" />
</segment>
<segment time="0.894507" length="0" sourcetrack="0"  >
	<beattype id="1" pattern="0" measure="0" beat="0" tatum="1" />
</segment>
<segment time="1.03769707679749" length="0" sourcetrack="0"  >
	<beattype id="1" pattern="0" measure="0" beat="1" tatum="1" />
</segment>
<segment time="1.327947" length="0" sourcetrack="0"  >
	<beattype id="1" pattern="0" measure="0" beat="0" tatum="1" />
</segment>
<segment time="1.47307121753693" length="0" sourcetrack="0"  >
	<beattype id="1" pattern="0" measure="1" beat="1" tatum="1" />
</segment>
<segment time="1.759451" length="0" sourcetrack="0"  >
	<beattype id="1" pattern="0" measure="0" beat="0" tatum="1" />
</segment>
<segment time="1.9026403427124" length="0" sourcetrack="0"  >
	<beattype id="1" pattern="0" measure="0" beat="1" tatum="1" />
</segment>
<segment time="2.18902" length="0" sourcetrack="0"  >
	<beattype id="1" pattern="0" measure="0" beat="0" tatum="1" />
</segment>
<segment time="2.33220958709717" length="0" sourcetrack="0"  >
	<beattype id="1" pattern="0" measure="0" beat="1" tatum="1" />
</segment>
<segment time="2.60848" length="0" sourcetrack="0"  >
	<beattype id="1" pattern="0" measure="0" beat="0" tatum="1" />
</segment>
<segment time="2.74661540985107" length="0" sourcetrack="0"  >
	<beattype id="1" pattern="0" measure="0" beat="1" tatum="1" />
</segment>
<segment time="3.03489" length="0" sourcetrack="0"  >
	<beattype id="1" pattern="0" measure="0" beat="0" tatum="1" />
</segment>
<segment time="3.17902708053589" length="0" sourcetrack="0"  >
	<beattype id="1" pattern="0" measure="1" beat="1" tatum="1" />
</segment>
<segment time="3.48136" length="0" sourcetrack="0"  >
	<beattype id="1" pattern="0" measure="0" beat="0" tatum="1" />
</segment>
<segment time="3.63252687454224" length="0" sourcetrack="0"  >
	<beattype id="1" pattern="0" measure="0" beat="1" tatum="1" />
</segment>
<segment time="3.918906" length="0" sourcetrack="0"  >
	<beattype id="1" pattern="0" measure="0" beat="0" tatum="1" />
</segment>
<segment time="4.062096118927" length="0" sourcetrack="0"  >
	<beattype id="1" pattern="0" measure="0" beat="1" tatum="1" />
</segment>
<segment time="4.344606" length="0" sourcetrack="0"  >
	<beattype id="1" pattern="0" measure="0" beat="0" tatum="1" />
</segment>
<segment time="4.4858603477478" length="0" sourcetrack="0"  >
	<beattype id="1" pattern="0" measure="0" beat="1" tatum="1" />
</segment>
<segment time="4.77224" length="0" sourcetrack="0"  >
	<beattype id="1" pattern="0" measure="0" beat="0" tatum="1" />
</segment>
<segment time="4.91542959213257" length="0" sourcetrack="0"  >
	<beattype id="1" pattern="0" measure="1" beat="1" tatum="1" />
</segment>
<segment time="5.193862" length="0" sourcetrack="0"  >
	<beattype id="1" pattern="0" measure="0" beat="0" tatum="1" />
</segment>
<segment time="5.33307838439941" length="0" sourcetrack="0"  >
	<beattype id="1" pattern="0" measure="0" beat="1" tatum="1" />
</segment>
<segment time="5.631275" length="0" sourcetrack="0"  >
	<beattype id="1" pattern="0" measure="0" beat="0" tatum="1" />
</segment>
<segment time="5.78037261962891" length="0" sourcetrack="0"  >
	<beattype id="1" pattern="0" measure="0" beat="1" tatum="1" />
</segment>
<segment time="6.066752" length="0" sourcetrack="0"  >
	<beattype id="1" pattern="0" measure="0" beat="0" tatum="1" />
</segment>
<segment time="6.20994186401367" length="0" sourcetrack="0"  >
	<beattype id="1" pattern="0" measure="0" beat="1" tatum="1" />
</segment>
<segment time="6.49019" length="0" sourcetrack="0"  >
	<beattype id="1" pattern="0" measure="0" beat="0" tatum="1" />
</segment>
<segment time="6.63031339645386" length="0" sourcetrack="0"  >
	<beattype id="1" pattern="0" measure="1" beat="1" tatum="1" />
</segment>
<segment time="6.926695" length="0" sourcetrack="0"  >
	<beattype id="1" pattern="0" measure="0" beat="0" tatum="1" />
</segment>
<segment time="7.07488536834717" length="0" sourcetrack="0"  >
	<beattype id="1" pattern="0" measure="0" beat="1" tatum="1" />
</segment>
<segment time="7.361265" length="0" sourcetrack="0"  >
	<beattype id="1" pattern="0" measure="0" beat="0" tatum="1" />
</segment>
<segment time="7.50445461273193" length="0" sourcetrack="0"  >
	<beattype id="1" pattern="0" measure="0" beat="1" tatum="1" />
</segment>
<segment time="7.790834" length="0" sourcetrack="0"  >
	<beattype id="1" pattern="0" measure="0" beat="0" tatum="1" />
</segment>
<segment time="7.93402338027954" length="0" sourcetrack="0"  >
	<beattype id="1" pattern="0" measure="0" beat="1" tatum="1" />
</segment>
<segment time="8.220403" length="0" sourcetrack="0"  >
	<beattype id="1" pattern="0" measure="0" beat="0" tatum="1" />
</segment>
<segment time="8.36359310150146" length="0" sourcetrack="0"  >
	<beattype id="1" pattern="0" measure="1" beat="1" tatum="1" />
</segment>
<segment time="8.646103" length="0" sourcetrack="0"  >
	<beattype id="1" pattern="0" measure="0" beat="0" tatum="1" />
</segment>
<segment time="8.78735733032227" length="0" sourcetrack="0"  >
	<beattype id="1" pattern="0" measure="0" beat="1" tatum="1" />
</segment>
<segment time="9.073736" length="0" sourcetrack="0"  >
	<beattype id="1" pattern="0" measure="0" beat="0" tatum="1" />
</segment>
<segment time="9.21692562103271" length="0" sourcetrack="0"  >
	<beattype id="1" pattern="0" measure="0" beat="1" tatum="1" />
</segment>
<segment time="9.503305" length="0" sourcetrack="0"  >
	<beattype id="1" pattern="0" measure="0" beat="0" tatum="1" />
</segment>
<segment time="9.64649486541748" length="0" sourcetrack="0"  >
	<beattype id="1" pattern="0" measure="0" beat="1" tatum="1" />
</segment>
<segment time="9.932874" length="0" sourcetrack="0"  >
	<beattype id="1" pattern="0" measure="0" beat="0" tatum="1" />
</segment>
<segment time="10.0760641098022" length="0" sourcetrack="0"  >
	<beattype id="1" pattern="0" measure="1" beat="1" tatum="1" />
</segment>
<segment time="10.362444" length="0" sourcetrack="0"  >
	<beattype id="1" pattern="0" measure="0" beat="0" tatum="1" />
</segment>
<segment time="10.505633354187" length="0" sourcetrack="0"  >
	<beattype id="1" pattern="0" measure="0" beat="1" tatum="1" />
</segment>
<segment time="10.792013" length="0" sourcetrack="0"  >
	<beattype id="1" pattern="0" measure="0" beat="0" tatum="1" />
</segment>
<segment time="10.9352025985718" length="0" sourcetrack="0"  >
	<beattype id="1" pattern="0" measure="0" beat="1" tatum="1" />
</segment>
<segment time="11.221582" length="0" sourcetrack="0"  >
	<beattype id="1" pattern="0" measure="0" beat="0" tatum="1" />
</segment>
<segment time="11.3647718429565" length="0" sourcetrack="0"  >
	<beattype id="1" pattern="0" measure="0" beat="1" tatum="1" />
</segment>
<segment time="11.651151" length="0" sourcetrack="0"  >
	<beattype id="1" pattern="0" measure="0" beat="0" tatum="1" />
</segment>
<segment time="11.7943410873413" length="0" sourcetrack="0"  >
	<beattype id="1" pattern="0" measure="1" beat="1" tatum="1" />
</segment>
<segment time="12.084591" length="0" sourcetrack="0"  >
	<beattype id="1" pattern="0" measure="0" beat="0" tatum="1" />
</segment>
<segment time="12.22971534729" length="0" sourcetrack="0"  >
	<beattype id="1" pattern="0" measure="0" beat="1" tatum="1" />
</segment>
<segment time="12.512225" length="0" sourcetrack="0"  >
	<beattype id="1" pattern="0" measure="0" beat="0" tatum="1" />
</segment>
<segment time="12.6534795761108" length="0" sourcetrack="0"  >
	<beattype id="1" pattern="0" measure="0" beat="1" tatum="1" />
</segment>
<segment time="12.943729" length="0" sourcetrack="0"  >
	<beattype id="1" pattern="0" measure="0" beat="0" tatum="1" />
</segment>
<segment time="13.0888538360596" length="0" sourcetrack="0"  >
	<beattype id="1" pattern="0" measure="0" beat="1" tatum="1" />
</segment>
<segment time="13.375233" length="0" sourcetrack="0"  >
	<beattype id="1" pattern="0" measure="0" beat="0" tatum="1" />
</segment>
<segment time="13.5184230804443" length="0" sourcetrack="0"  >
	<beattype id="1" pattern="0" measure="1" beat="1" tatum="1" />
</segment>
<segment time="13.804802" length="0" sourcetrack="0"  >
	<beattype id="1" pattern="0" measure="0" beat="0" tatum="1" />
</segment>
<segment time="13.9479913711548" length="0" sourcetrack="0"  >
	<beattype id="1" pattern="0" measure="0" beat="1" tatum="1" />
</segment>
<segment time="14.234371" length="0" sourcetrack="0"  >
	<beattype id="1" pattern="0" measure="0" beat="0" tatum="1" />
</segment>
<segment time="14.3775606155396" length="0" sourcetrack="0"  >
	<beattype id="1" pattern="0" measure="0" beat="1" tatum="1" />
</segment>
<segment time="14.66394" length="0" sourcetrack="0"  >
	<beattype id="1" pattern="0" measure="0" beat="0" tatum="1" />
</segment>
<segment time="14.8071298599243" length="0" sourcetrack="0"  >
	<beattype id="1" pattern="0" measure="0" beat="1" tatum="1" />
</segment>
<segment time="15.093509" length="0" sourcetrack="0"  >
	<beattype id="1" pattern="0" measure="0" beat="0" tatum="1" />
</segment>
<segment time="15.2366991043091" length="0" sourcetrack="0"  >
	<beattype id="1" pattern="0" measure="1" beat="1" tatum="1" />
</segment>
<segment time="15.523079" length="0" sourcetrack="0"  >
	<beattype id="1" pattern="0" measure="0" beat="0" tatum="1" />
</segment>
<segment time="15.6662683486938" length="0" sourcetrack="0"  >
	<beattype id="1" pattern="0" measure="0" beat="1" tatum="1" />
</segment>
<segment time="15.952648" length="0" sourcetrack="0"  >
	<beattype id="1" pattern="0" measure="0" beat="0" tatum="1" />
</segment>
<segment time="16.0958385467529" length="0" sourcetrack="0"  >
	<beattype id="1" pattern="0" measure="0" beat="1" tatum="1" />
</segment>
<segment time="16.386087" length="0" sourcetrack="0"  >
	<beattype id="1" pattern="0" measure="0" beat="0" tatum="1" />
</segment>
<segment time="16.5312118530273" length="0" sourcetrack="0"  >
	<beattype id="1" pattern="0" measure="0" beat="1" tatum="1" />
</segment>
<segment time="16.817591" length="0" sourcetrack="0"  >
	<beattype id="1" pattern="0" measure="0" beat="0" tatum="1" />
</segment>
<segment time="16.9607810974121" length="0" sourcetrack="0"  >
	<beattype id="1" pattern="0" measure="1" beat="1" tatum="1" />
</segment>
<segment time="17.247161" length="0" sourcetrack="0"  >
	<beattype id="1" pattern="0" measure="0" beat="0" tatum="1" />
</segment>
<segment time="17.3903503417969" length="0" sourcetrack="0"  >
	<beattype id="1" pattern="0" measure="0" beat="1" tatum="1" />
</segment>
<segment time="17.680599" length="0" sourcetrack="0"  >
	<beattype id="1" pattern="0" measure="0" beat="0" tatum="1" />
</segment>
<segment time="17.8257236480713" length="0" sourcetrack="0"  >
	<beattype id="1" pattern="0" measure="0" beat="1" tatum="1" />
</segment>
<segment time="18.112103" length="0" sourcetrack="0"  >
	<beattype id="1" pattern="0" measure="0" beat="0" tatum="1" />
</segment>
<segment time="18.2552928924561" length="0" sourcetrack="0"  >
	<beattype id="1" pattern="0" measure="0" beat="1" tatum="1" />
</segment>
<segment time="18.545543" length="0" sourcetrack="0"  >
	<beattype id="1" pattern="0" measure="0" beat="0" tatum="1" />
</segment>
<segment time="18.6906681060791" length="0" sourcetrack="0"  >
	<beattype id="1" pattern="0" measure="1" beat="1" tatum="1" />
</segment>
<segment time="18.977048" length="0" sourcetrack="0"  >
	<beattype id="1" pattern="0" measure="0" beat="0" tatum="1" />
</segment>
<segment time="19.1202373504639" length="0" sourcetrack="0"  >
	<beattype id="1" pattern="0" measure="0" beat="1" tatum="1" />
</segment>
<segment time="19.410486" length="0" sourcetrack="0"  >
	<beattype id="1" pattern="0" measure="0" beat="0" tatum="1" />
</segment>
<segment time="19.5556106567383" length="0" sourcetrack="0"  >
	<beattype id="1" pattern="0" measure="0" beat="1" tatum="1" />
</segment>
<segment time="19.84199" length="0" sourcetrack="0"  >
	<beattype id="1" pattern="0" measure="0" beat="0" tatum="1" />
</segment>
<segment time="19.985179901123" length="0" sourcetrack="0"  >
	<beattype id="1" pattern="0" measure="0" beat="1" tatum="1" />
</segment>
<segment time="20.267403" length="0" sourcetrack="0"  >
	<beattype id="1" pattern="0" measure="0" beat="0" tatum="1" />
</segment>
<segment time="20.4085140228271" length="0" sourcetrack="0"  >
	<beattype id="1" pattern="0" measure="1" beat="1" tatum="1" />
</segment>
<segment time="20.702127" length="0" sourcetrack="0"  >
	<beattype id="1" pattern="0" measure="0" beat="0" tatum="1" />
</segment>
<segment time="20.848934173584" length="0" sourcetrack="0"  >
	<beattype id="1" pattern="0" measure="0" beat="1" tatum="1" />
</segment>
<segment time="21.135314" length="0" sourcetrack="0"  >
	<beattype id="1" pattern="0" measure="0" beat="0" tatum="1" />
</segment>
<segment time="21.2785034179688" length="0" sourcetrack="0"  >
	<beattype id="1" pattern="0" measure="0" beat="1" tatum="1" />
</segment>
<segment time="21.568752" length="0" sourcetrack="0"  >
	<beattype id="1" pattern="0" measure="0" beat="0" tatum="1" />
</segment>
<segment time="21.7138767242432" length="0" sourcetrack="0"  >
	<beattype id="1" pattern="0" measure="0" beat="1" tatum="1" />
</segment>
<segment time="22.000256" length="0" sourcetrack="0"  >
	<beattype id="1" pattern="0" measure="0" beat="0" tatum="1" />
</segment>
<segment time="22.1434459686279" length="0" sourcetrack="0"  >
	<beattype id="1" pattern="0" measure="1" beat="1" tatum="1" />
</segment>
<segment time="22.433696" length="0" sourcetrack="0"  >
	<beattype id="1" pattern="0" measure="0" beat="0" tatum="1" />
</segment>
<segment time="22.578821182251" length="0" sourcetrack="0"  >
	<beattype id="1" pattern="0" measure="0" beat="1" tatum="1" />
</segment>
<segment time="22.865201" length="0" sourcetrack="0"  >
	<beattype id="1" pattern="0" measure="0" beat="0" tatum="1" />
</segment>
<segment time="23.0083904266357" length="0" sourcetrack="0"  >
	<beattype id="1" pattern="0" measure="0" beat="1" tatum="1" />
</segment>
<segment time="23.298639" length="0" sourcetrack="0"  >
	<beattype id="1" pattern="0" measure="0" beat="0" tatum="1" />
</segment>
<segment time="23.4437637329102" length="0" sourcetrack="0"  >
	<beattype id="1" pattern="0" measure="0" beat="1" tatum="1" />
</segment>
<segment time="23.730143" length="0" sourcetrack="0"  >
	<beattype id="1" pattern="0" measure="0" beat="0" tatum="1" />
</segment>
<segment time="23.8733329772949" length="0" sourcetrack="0"  >
	<beattype id="1" pattern="0" measure="1" beat="1" tatum="1" />
</segment>
<segment time="24.159712" length="0" sourcetrack="0"  >
	<beattype id="1" pattern="0" measure="0" beat="0" tatum="1" />
</segment>
<segment time="24.3029022216797" length="0" sourcetrack="0"  >
	<beattype id="1" pattern="0" measure="0" beat="1" tatum="1" />
</segment>
<segment time="24.599087" length="0" sourcetrack="0"  >
	<beattype id="1" pattern="0" measure="0" beat="0" tatum="1" />
</segment>
<segment time="24.7471790313721" length="0" sourcetrack="0"  >
	<beattype id="1" pattern="0" measure="0" beat="1" tatum="1" />
</segment>
<segment time="25.027623" length="0" sourcetrack="0"  >
	<beattype id="1" pattern="0" measure="0" beat="0" tatum="1" />
</segment>
<segment time="25.1678447723389" length="0" sourcetrack="0"  >
	<beattype id="1" pattern="0" measure="0" beat="1" tatum="1" />
</segment>
<segment time="25.458095" length="0" sourcetrack="0"  >
	<beattype id="1" pattern="0" measure="0" beat="0" tatum="1" />
</segment>
<segment time="25.6032199859619" length="0" sourcetrack="0"  >
	<beattype id="1" pattern="0" measure="1" beat="1" tatum="1" />
</segment>
<segment time="25.893469" length="0" sourcetrack="0"  >
	<beattype id="1" pattern="0" measure="0" beat="0" tatum="1" />
</segment>
<segment time="26.0385932922363" length="0" sourcetrack="0"  >
	<beattype id="1" pattern="0" measure="0" beat="1" tatum="1" />
</segment>
<segment time="26.332713" length="0" sourcetrack="0"  >
	<beattype id="1" pattern="0" measure="0" beat="0" tatum="1" />
</segment>
<segment time="26.479772567749" length="0" sourcetrack="0"  >
	<beattype id="1" pattern="0" measure="0" beat="1" tatum="1" />
</segment>
<segment time="26.770023" length="0" sourcetrack="0"  >
	<beattype id="1" pattern="0" measure="0" beat="0" tatum="1" />
</segment>
<segment time="26.9151477813721" length="0" sourcetrack="0"  >
	<beattype id="1" pattern="0" measure="0" beat="1" tatum="1" />
</segment>
<segment time="27.201527" length="0" sourcetrack="0"  >
	<beattype id="1" pattern="0" measure="0" beat="0" tatum="1" />
</segment>
<segment time="27.3447170257568" length="0" sourcetrack="0"  >
	<beattype id="1" pattern="0" measure="1" beat="1" tatum="1" />
</segment>
<segment time="27.631097" length="0" sourcetrack="0"  >
	<beattype id="1" pattern="0" measure="0" beat="0" tatum="1" />
</segment>
<segment time="27.7742862701416" length="0" sourcetrack="0"  >
	<beattype id="1" pattern="0" measure="0" beat="1" tatum="1" />
</segment>
<segment time="28.060664" length="0" sourcetrack="0"  >
	<beattype id="1" pattern="0" measure="0" beat="0" tatum="1" />
</segment>
<segment time="28.2038536071777" length="0" sourcetrack="0"  >
	<beattype id="1" pattern="0" measure="0" beat="1" tatum="1" />
</segment>
<segment time="28.490233" length="0" sourcetrack="0"  >
	<beattype id="1" pattern="0" measure="0" beat="0" tatum="1" />
</segment>
<segment time="28.6334228515625" length="0" sourcetrack="0"  >
	<beattype id="1" pattern="0" measure="0" beat="1" tatum="1" />
</segment>
<segment time="28.920001" length="0" sourcetrack="0"  >
	<beattype id="1" pattern="0" measure="0" beat="0" tatum="1" />
</segment>
<segment time="29.063289642334" length="0" sourcetrack="0"  >
	<beattype id="1" pattern="0" measure="1" beat="1" tatum="1" />
</segment>
<segment time="29.346226" length="0" sourcetrack="0"  >
	<beattype id="1" pattern="0" measure="0" beat="0" tatum="1" />
</segment>
<segment time="29.4876937866211" length="0" sourcetrack="0"  >
	<beattype id="1" pattern="0" measure="0" beat="1" tatum="1" />
</segment>
</musicdescription>
