<?xml version="1.0" encoding="UTF-8" standalone="yes" ?>
<musicdescription xmlns="http://www.ircam.fr/musicdescription/1.1" xmlns:xsi="http://www.w3.org/2001/XMLSchema-instance" xsi:schemaLocation="http://www.ircam.fr/musicdescription/1.1 http://recherche.ircam.fr/anasyn/xsd/musicdescription_1.1.xsd" format="20140305A" date="2015-10-28" >
<media>./metal/metal.00011.wav</media>
<descriptiondefinition id="1" >
	<type>beattype</type>
	<generator name="AudioSculpt" version="3.2.91" date="2015-10-28" />
</descriptiondefinition>
<segment time="0.0624589547514915" length="0" sourcetrack="0"  >
	<beattype id="1" pattern="0" measure="1" beat="1" tatum="1" />
</segment>
<segment time="0.422368258237839" length="0" sourcetrack="0"  >
	<beattype id="1" pattern="0" measure="0" beat="1" tatum="1" />
</segment>
<segment time="0.788082540035248" length="0" sourcetrack="0"  >
	<beattype id="1" pattern="0" measure="0" beat="1" tatum="1" />
</segment>
<segment time="1.15379679203033" length="0" sourcetrack="0"  >
	<beattype id="1" pattern="0" measure="0" beat="1" tatum="1" />
</segment>
<segment time="1.51951110363007" length="0" sourcetrack="0"  >
	<beattype id="1" pattern="0" measure="1" beat="1" tatum="1" />
</segment>
<segment time="1.86781048774719" length="0" sourcetrack="0"  >
	<beattype id="1" pattern="0" measure="0" beat="1" tatum="1" />
</segment>
<segment time="2.23352479934692" length="0" sourcetrack="0"  >
	<beattype id="1" pattern="0" measure="0" beat="1" tatum="1" />
</segment>
<segment time="2.60504388809204" length="0" sourcetrack="0"  >
	<beattype id="1" pattern="0" measure="0" beat="1" tatum="1" />
</segment>
<segment time="2.97075819969177" length="0" sourcetrack="0"  >
	<beattype id="1" pattern="0" measure="1" beat="1" tatum="1" />
</segment>
<segment time="3.34227752685547" length="0" sourcetrack="0"  >
	<beattype id="1" pattern="0" measure="0" beat="1" tatum="1" />
</segment>
<segment time="3.7079918384552" length="0" sourcetrack="0"  >
	<beattype id="1" pattern="0" measure="0" beat="1" tatum="1" />
</segment>
<segment time="4.0795111656189" length="0" sourcetrack="0"  >
	<beattype id="1" pattern="0" measure="0" beat="1" tatum="1" />
</segment>
<segment time="4.44522523880005" length="0" sourcetrack="0"  >
	<beattype id="1" pattern="0" measure="1" beat="1" tatum="1" />
</segment>
<segment time="4.81674480438232" length="0" sourcetrack="0"  >
	<beattype id="1" pattern="0" measure="0" beat="1" tatum="1" />
</segment>
<segment time="5.18245887756348" length="0" sourcetrack="0"  >
	<beattype id="1" pattern="0" measure="0" beat="1" tatum="1" />
</segment>
<segment time="5.54817342758179" length="0" sourcetrack="0"  >
	<beattype id="1" pattern="0" measure="0" beat="1" tatum="1" />
</segment>
<segment time="5.91388750076294" length="0" sourcetrack="0"  >
	<beattype id="1" pattern="0" measure="1" beat="1" tatum="1" />
</segment>
<segment time="6.27960205078125" length="0" sourcetrack="0"  >
	<beattype id="1" pattern="0" measure="0" beat="1" tatum="1" />
</segment>
<segment time="6.6453161239624" length="0" sourcetrack="0"  >
	<beattype id="1" pattern="0" measure="0" beat="1" tatum="1" />
</segment>
<segment time="7.01103019714355" length="0" sourcetrack="0"  >
	<beattype id="1" pattern="0" measure="0" beat="1" tatum="1" />
</segment>
<segment time="7.37674474716187" length="0" sourcetrack="0"  >
	<beattype id="1" pattern="0" measure="1" beat="1" tatum="1" />
</segment>
<segment time="7.74245882034302" length="0" sourcetrack="0"  >
	<beattype id="1" pattern="0" measure="0" beat="1" tatum="1" />
</segment>
<segment time="8.11397838592529" length="0" sourcetrack="0"  >
	<beattype id="1" pattern="0" measure="0" beat="1" tatum="1" />
</segment>
<segment time="8.47969245910645" length="0" sourcetrack="0"  >
	<beattype id="1" pattern="0" measure="0" beat="1" tatum="1" />
</segment>
<segment time="8.85121154785156" length="0" sourcetrack="0"  >
	<beattype id="1" pattern="0" measure="1" beat="1" tatum="1" />
</segment>
<segment time="9.23434066772461" length="0" sourcetrack="0"  >
	<beattype id="1" pattern="0" measure="0" beat="1" tatum="1" />
</segment>
<segment time="9.70454502105713" length="0" sourcetrack="0"  >
	<beattype id="1" pattern="0" measure="0" beat="1" tatum="1" />
</segment>
<segment time="10.0702590942383" length="0" sourcetrack="0"  >
	<beattype id="1" pattern="0" measure="0" beat="1" tatum="1" />
</segment>
<segment time="10.4359741210938" length="0" sourcetrack="0"  >
	<beattype id="1" pattern="0" measure="1" beat="1" tatum="1" />
</segment>
<segment time="10.8016881942749" length="0" sourcetrack="0"  >
	<beattype id="1" pattern="0" measure="0" beat="1" tatum="1" />
</segment>
<segment time="11.1615972518921" length="0" sourcetrack="0"  >
	<beattype id="1" pattern="0" measure="0" beat="1" tatum="1" />
</segment>
<segment time="11.5273113250732" length="0" sourcetrack="0"  >
	<beattype id="1" pattern="0" measure="0" beat="1" tatum="1" />
</segment>
<segment time="11.8988304138184" length="0" sourcetrack="0"  >
	<beattype id="1" pattern="0" measure="1" beat="1" tatum="1" />
</segment>
<segment time="12.2587404251099" length="0" sourcetrack="0"  >
	<beattype id="1" pattern="0" measure="0" beat="1" tatum="1" />
</segment>
<segment time="12.6186494827271" length="0" sourcetrack="0"  >
	<beattype id="1" pattern="0" measure="0" beat="1" tatum="1" />
</segment>
<segment time="12.9843635559082" length="0" sourcetrack="0"  >
	<beattype id="1" pattern="0" measure="0" beat="1" tatum="1" />
</segment>
<segment time="13.3500776290894" length="0" sourcetrack="0"  >
	<beattype id="1" pattern="0" measure="1" beat="1" tatum="1" />
</segment>
<segment time="13.7215976715088" length="0" sourcetrack="0"  >
	<beattype id="1" pattern="0" measure="0" beat="1" tatum="1" />
</segment>
<segment time="14.0931167602539" length="0" sourcetrack="0"  >
	<beattype id="1" pattern="0" measure="0" beat="1" tatum="1" />
</segment>
<segment time="14.4878559112549" length="0" sourcetrack="0"  >
	<beattype id="1" pattern="0" measure="0" beat="1" tatum="1" />
</segment>
<segment time="14.859375" length="0" sourcetrack="0"  >
	<beattype id="1" pattern="0" measure="1" beat="1" tatum="1" />
</segment>
<segment time="15.2657241821289" length="0" sourcetrack="0"  >
	<beattype id="1" pattern="0" measure="0" beat="1" tatum="1" />
</segment>
<segment time="15.643048286438" length="0" sourcetrack="0"  >
	<beattype id="1" pattern="0" measure="0" beat="1" tatum="1" />
</segment>
<segment time="16.0087623596191" length="0" sourcetrack="0"  >
	<beattype id="1" pattern="0" measure="0" beat="1" tatum="1" />
</segment>
<segment time="16.3744773864746" length="0" sourcetrack="0"  >
	<beattype id="1" pattern="0" measure="1" beat="1" tatum="1" />
</segment>
<segment time="16.7401905059814" length="0" sourcetrack="0"  >
	<beattype id="1" pattern="0" measure="0" beat="1" tatum="1" />
</segment>
<segment time="17.1117115020752" length="0" sourcetrack="0"  >
	<beattype id="1" pattern="0" measure="0" beat="1" tatum="1" />
</segment>
<segment time="17.48903465271" length="0" sourcetrack="0"  >
	<beattype id="1" pattern="0" measure="0" beat="1" tatum="1" />
</segment>
<segment time="17.8605537414551" length="0" sourcetrack="0"  >
	<beattype id="1" pattern="0" measure="1" beat="1" tatum="1" />
</segment>
<segment time="18.2262687683105" length="0" sourcetrack="0"  >
	<beattype id="1" pattern="0" measure="0" beat="1" tatum="1" />
</segment>
<segment time="18.5919818878174" length="0" sourcetrack="0"  >
	<beattype id="1" pattern="0" measure="0" beat="1" tatum="1" />
</segment>
<segment time="19.0621871948242" length="0" sourcetrack="0"  >
	<beattype id="1" pattern="0" measure="0" beat="1" tatum="1" />
</segment>
<segment time="19.4337062835693" length="0" sourcetrack="0"  >
	<beattype id="1" pattern="0" measure="1" beat="1" tatum="1" />
</segment>
<segment time="19.7994213104248" length="0" sourcetrack="0"  >
	<beattype id="1" pattern="0" measure="0" beat="1" tatum="1" />
</segment>
<segment time="20.1651344299316" length="0" sourcetrack="0"  >
	<beattype id="1" pattern="0" measure="0" beat="1" tatum="1" />
</segment>
<segment time="20.5308494567871" length="0" sourcetrack="0"  >
	<beattype id="1" pattern="0" measure="0" beat="1" tatum="1" />
</segment>
<segment time="20.9720287322998" length="0" sourcetrack="0"  >
	<beattype id="1" pattern="0" measure="1" beat="1" tatum="1" />
</segment>
<segment time="21.4480381011963" length="0" sourcetrack="0"  >
	<beattype id="1" pattern="0" measure="0" beat="1" tatum="1" />
</segment>
<segment time="21.8485813140869" length="0" sourcetrack="0"  >
	<beattype id="1" pattern="0" measure="0" beat="1" tatum="1" />
</segment>
<segment time="22.2142963409424" length="0" sourcetrack="0"  >
	<beattype id="1" pattern="0" measure="0" beat="1" tatum="1" />
</segment>
<segment time="22.5800094604492" length="0" sourcetrack="0"  >
	<beattype id="1" pattern="0" measure="1" beat="1" tatum="1" />
</segment>
<segment time="22.9457244873047" length="0" sourcetrack="0"  >
	<beattype id="1" pattern="0" measure="0" beat="1" tatum="1" />
</segment>
<segment time="23.3114376068115" length="0" sourcetrack="0"  >
	<beattype id="1" pattern="0" measure="0" beat="1" tatum="1" />
</segment>
<segment time="23.6713485717773" length="0" sourcetrack="0"  >
	<beattype id="1" pattern="0" measure="0" beat="1" tatum="1" />
</segment>
<segment time="24.0370616912842" length="0" sourcetrack="0"  >
	<beattype id="1" pattern="0" measure="1" beat="1" tatum="1" />
</segment>
<segment time="24.4898509979248" length="0" sourcetrack="0"  >
	<beattype id="1" pattern="0" measure="0" beat="1" tatum="1" />
</segment>
<segment time="24.8555660247803" length="0" sourcetrack="0"  >
	<beattype id="1" pattern="0" measure="0" beat="1" tatum="1" />
</segment>
<segment time="25.3083553314209" length="0" sourcetrack="0"  >
	<beattype id="1" pattern="0" measure="0" beat="1" tatum="1" />
</segment>
<segment time="25.7437286376953" length="0" sourcetrack="0"  >
	<beattype id="1" pattern="0" measure="1" beat="1" tatum="1" />
</segment>
<segment time="26.1036376953125" length="0" sourcetrack="0"  >
	<beattype id="1" pattern="0" measure="0" beat="1" tatum="1" />
</segment>
<segment time="26.4809627532959" length="0" sourcetrack="0"  >
	<beattype id="1" pattern="0" measure="0" beat="1" tatum="1" />
</segment>
<segment time="26.8466758728027" length="0" sourcetrack="0"  >
	<beattype id="1" pattern="0" measure="0" beat="1" tatum="1" />
</segment>
<segment time="27.2181968688965" length="0" sourcetrack="0"  >
	<beattype id="1" pattern="0" measure="1" beat="1" tatum="1" />
</segment>
<segment time="27.6477642059326" length="0" sourcetrack="0"  >
	<beattype id="1" pattern="0" measure="0" beat="1" tatum="1" />
</segment>
<segment time="28.0947494506836" length="0" sourcetrack="0"  >
	<beattype id="1" pattern="0" measure="0" beat="1" tatum="1" />
</segment>
<segment time="28.4604625701904" length="0" sourcetrack="0"  >
	<beattype id="1" pattern="0" measure="0" beat="1" tatum="1" />
</segment>
<segment time="28.8261775970459" length="0" sourcetrack="0"  >
	<beattype id="1" pattern="0" measure="1" beat="1" tatum="1" />
</segment>
<segment time="29.1918926239014" length="0" sourcetrack="0"  >
	<beattype id="1" pattern="0" measure="0" beat="1" tatum="1" />
</segment>
<segment time="29.5401916503906" length="0" sourcetrack="0"  >
	<beattype id="1" pattern="0" measure="0" beat="1" tatum="1" />
</segment>
<segment time="29.8536605834961" length="0" sourcetrack="0"  >
	<beattype id="1" pattern="0" measure="0" beat="1" tatum="1" />
</segment>
</musicdescription>
