<?xml version="1.0" encoding="UTF-8" standalone="yes" ?>
<musicdescription xmlns="http://www.ircam.fr/musicdescription/1.1" xmlns:xsi="http://www.w3.org/2001/XMLSchema-instance" xsi:schemaLocation="http://www.ircam.fr/musicdescription/1.1 http://recherche.ircam.fr/anasyn/xsd/musicdescription_1.1.xsd" format="20140305A" date="2015-10-28" >
<media>./reggae/reggae.00059.wav</media>
<descriptiondefinition id="1" >
	<type>beattype</type>
	<generator name="AudioSculpt" version="3.3.9" date="2015-10-28" />
</descriptiondefinition>
<segment time="0.16666667163372" length="0" sourcetrack="0"  >
	<beattype id="1" pattern="0" measure="1" beat="1" tatum="1" />
</segment>
<segment time="0.55354686797474" length="0" sourcetrack="0"  >
	<beattype id="1" pattern="0" measure="0" beat="1" tatum="1" />
</segment>
<segment time="0.940427064315759" length="0" sourcetrack="0"  >
	<beattype id="1" pattern="0" measure="0" beat="1" tatum="1" />
</segment>
<segment time="1.33655360885305" length="0" sourcetrack="0"  >
	<beattype id="1" pattern="0" measure="0" beat="1" tatum="1" />
</segment>
<segment time="1.73268015339034" length="0" sourcetrack="0"  >
	<beattype id="1" pattern="0" measure="1" beat="1" tatum="1" />
</segment>
<segment time="2.12480934116829" length="0" sourcetrack="0"  >
	<beattype id="1" pattern="0" measure="0" beat="1" tatum="1" />
</segment>
<segment time="2.51693852894624" length="0" sourcetrack="0"  >
	<beattype id="1" pattern="0" measure="0" beat="1" tatum="1" />
</segment>
<segment time="2.91294688700676" length="0" sourcetrack="0"  >
	<beattype id="1" pattern="0" measure="0" beat="1" tatum="1" />
</segment>
<segment time="3.30895519256592" length="0" sourcetrack="0"  >
	<beattype id="1" pattern="0" measure="1" beat="1" tatum="1" />
</segment>
<segment time="3.69081536775677" length="0" sourcetrack="0"  >
	<beattype id="1" pattern="0" measure="0" beat="1" tatum="1" />
</segment>
<segment time="4.07267549044624" length="0" sourcetrack="0"  >
	<beattype id="1" pattern="0" measure="0" beat="1" tatum="1" />
</segment>
<segment time="4.46160973079624" length="0" sourcetrack="0"  >
	<beattype id="1" pattern="0" measure="0" beat="1" tatum="1" />
</segment>
<segment time="4.85054397114624" length="0" sourcetrack="0"  >
	<beattype id="1" pattern="0" measure="1" beat="1" tatum="1" />
</segment>
<segment time="5.23947821154624" length="0" sourcetrack="0"  >
	<beattype id="1" pattern="0" measure="0" beat="1" tatum="1" />
</segment>
<segment time="5.62841245194624" length="0" sourcetrack="0"  >
	<beattype id="1" pattern="0" measure="0" beat="1" tatum="1" />
</segment>
<segment time="5.88607692718506" length="0" sourcetrack="0"  >
	<beattype id="1" pattern="0" measure="0" beat="0" tatum="1" />
</segment>
<segment time="6.01734669229624" length="0" sourcetrack="0"  >
	<beattype id="1" pattern="0" measure="0" beat="1" tatum="1" />
</segment>
<segment time="6.40628093264624" length="0" sourcetrack="0"  >
	<beattype id="1" pattern="0" measure="1" beat="1" tatum="1" />
</segment>
<segment time="6.79521517299624" length="0" sourcetrack="0"  >
	<beattype id="1" pattern="0" measure="0" beat="1" tatum="1" />
</segment>
<segment time="7.18414941334624" length="0" sourcetrack="0"  >
	<beattype id="1" pattern="0" measure="0" beat="1" tatum="1" />
</segment>
<segment time="7.57308365369624" length="0" sourcetrack="0"  >
	<beattype id="1" pattern="0" measure="0" beat="1" tatum="1" />
</segment>
<segment time="7.96201789404624" length="0" sourcetrack="0"  >
	<beattype id="1" pattern="0" measure="1" beat="1" tatum="1" />
</segment>
<segment time="8.35095213444624" length="0" sourcetrack="0"  >
	<beattype id="1" pattern="0" measure="0" beat="1" tatum="1" />
</segment>
<segment time="8.6030387878418" length="0" sourcetrack="0"  >
	<beattype id="1" pattern="0" measure="0" beat="0" tatum="1" />
</segment>
<segment time="8.73988637484624" length="0" sourcetrack="0"  >
	<beattype id="1" pattern="0" measure="0" beat="1" tatum="1" />
</segment>
<segment time="9.12882061519624" length="0" sourcetrack="0"  >
	<beattype id="1" pattern="0" measure="0" beat="1" tatum="1" />
</segment>
<segment time="9.51775485554624" length="0" sourcetrack="0"  >
	<beattype id="1" pattern="0" measure="1" beat="1" tatum="1" />
</segment>
<segment time="9.76344680786133" length="0" sourcetrack="0"  >
	<beattype id="1" pattern="0" measure="0" beat="0" tatum="1" />
</segment>
<segment time="9.90668909589622" length="0" sourcetrack="0"  >
	<beattype id="1" pattern="0" measure="0" beat="1" tatum="1" />
</segment>
<segment time="10.2956233362462" length="0" sourcetrack="0"  >
	<beattype id="1" pattern="0" measure="0" beat="1" tatum="1" />
</segment>
<segment time="10.6845575765962" length="0" sourcetrack="0"  >
	<beattype id="1" pattern="0" measure="0" beat="1" tatum="1" />
</segment>
<segment time="11.0734918169462" length="0" sourcetrack="0"  >
	<beattype id="1" pattern="0" measure="1" beat="1" tatum="1" />
</segment>
<segment time="11.4624260573462" length="0" sourcetrack="0"  >
	<beattype id="1" pattern="0" measure="0" beat="1" tatum="1" />
</segment>
<segment time="11.652153968811" length="0" sourcetrack="0"  >
	<beattype id="1" pattern="0" measure="0" beat="0" tatum="1" />
</segment>
<segment time="11.8513602977462" length="0" sourcetrack="0"  >
	<beattype id="1" pattern="0" measure="0" beat="1" tatum="1" />
</segment>
<segment time="12.2402945380962" length="0" sourcetrack="0"  >
	<beattype id="1" pattern="0" measure="0" beat="1" tatum="1" />
</segment>
<segment time="12.6292287784462" length="0" sourcetrack="0"  >
	<beattype id="1" pattern="0" measure="1" beat="1" tatum="1" />
</segment>
<segment time="13.0181630187962" length="0" sourcetrack="0"  >
	<beattype id="1" pattern="0" measure="0" beat="1" tatum="1" />
</segment>
<segment time="13.4070972591462" length="0" sourcetrack="0"  >
	<beattype id="1" pattern="0" measure="0" beat="1" tatum="1" />
</segment>
<segment time="13.7960314994962" length="0" sourcetrack="0"  >
	<beattype id="1" pattern="0" measure="0" beat="1" tatum="1" />
</segment>
<segment time="14.1849657398462" length="0" sourcetrack="0"  >
	<beattype id="1" pattern="0" measure="1" beat="1" tatum="1" />
</segment>
<segment time="14.5709974858962" length="0" sourcetrack="0"  >
	<beattype id="1" pattern="0" measure="0" beat="1" tatum="1" />
</segment>
<segment time="14.8153743743896" length="0" sourcetrack="0"  >
	<beattype id="1" pattern="0" measure="0" beat="0" tatum="1" />
</segment>
<segment time="14.9570292319462" length="0" sourcetrack="0"  >
	<beattype id="1" pattern="0" measure="0" beat="1" tatum="1" />
</segment>
<segment time="15.3459634722962" length="0" sourcetrack="0"  >
	<beattype id="1" pattern="0" measure="0" beat="1" tatum="1" />
</segment>
<segment time="15.7348977126462" length="0" sourcetrack="0"  >
	<beattype id="1" pattern="0" measure="1" beat="1" tatum="1" />
</segment>
<segment time="15.9676189422607" length="0" sourcetrack="0"  >
	<beattype id="1" pattern="0" measure="0" beat="0" tatum="1" />
</segment>
<segment time="16.1238319529962" length="0" sourcetrack="0"  >
	<beattype id="1" pattern="0" measure="0" beat="1" tatum="1" />
</segment>
<segment time="16.3902034759521" length="0" sourcetrack="0"  >
	<beattype id="1" pattern="0" measure="0" beat="0" tatum="1" />
</segment>
<segment time="16.5127661933462" length="0" sourcetrack="0"  >
	<beattype id="1" pattern="0" measure="0" beat="1" tatum="1" />
</segment>
<segment time="16.8987979393962" length="0" sourcetrack="0"  >
	<beattype id="1" pattern="0" measure="0" beat="1" tatum="1" />
</segment>
<segment time="17.2848296854462" length="0" sourcetrack="0"  >
	<beattype id="1" pattern="0" measure="1" beat="1" tatum="1" />
</segment>
<segment time="17.5078010559082" length="0" sourcetrack="0"  >
	<beattype id="1" pattern="0" measure="0" beat="0" tatum="1" />
</segment>
<segment time="17.6737639257962" length="0" sourcetrack="0"  >
	<beattype id="1" pattern="0" measure="0" beat="1" tatum="1" />
</segment>
<segment time="18.0626981661462" length="0" sourcetrack="0"  >
	<beattype id="1" pattern="0" measure="0" beat="1" tatum="1" />
</segment>
<segment time="18.4516324065462" length="0" sourcetrack="0"  >
	<beattype id="1" pattern="0" measure="0" beat="1" tatum="1" />
</segment>
<segment time="18.8405666469462" length="0" sourcetrack="0"  >
	<beattype id="1" pattern="0" measure="1" beat="1" tatum="1" />
</segment>
<segment time="19.0753746032715" length="0" sourcetrack="0"  >
	<beattype id="1" pattern="0" measure="0" beat="0" tatum="1" />
</segment>
<segment time="19.2295008872962" length="0" sourcetrack="0"  >
	<beattype id="1" pattern="0" measure="0" beat="1" tatum="1" />
</segment>
<segment time="19.4702033996582" length="0" sourcetrack="0"  >
	<beattype id="1" pattern="0" measure="0" beat="0" tatum="1" />
</segment>
<segment time="19.6184351276462" length="0" sourcetrack="0"  >
	<beattype id="1" pattern="0" measure="0" beat="1" tatum="1" />
</segment>
<segment time="20.0102118077783" length="0" sourcetrack="0"  >
	<beattype id="1" pattern="0" measure="0" beat="1" tatum="1" />
</segment>
<segment time="20.4019884879103" length="0" sourcetrack="0"  >
	<beattype id="1" pattern="0" measure="1" beat="1" tatum="1" />
</segment>
<segment time="20.7898832232554" length="0" sourcetrack="0"  >
	<beattype id="1" pattern="0" measure="0" beat="1" tatum="1" />
</segment>
<segment time="21.0436725616455" length="0" sourcetrack="0"  >
	<beattype id="1" pattern="0" measure="0" beat="0" tatum="1" />
</segment>
<segment time="21.1777779586005" length="0" sourcetrack="0"  >
	<beattype id="1" pattern="0" measure="0" beat="1" tatum="1" />
</segment>
<segment time="21.4303855895996" length="0" sourcetrack="0"  >
	<beattype id="1" pattern="0" measure="0" beat="0" tatum="1" />
</segment>
<segment time="21.5620067698733" length="0" sourcetrack="0"  >
	<beattype id="1" pattern="0" measure="0" beat="1" tatum="1" />
</segment>
<segment time="21.9462355811462" length="0" sourcetrack="0"  >
	<beattype id="1" pattern="0" measure="1" beat="1" tatum="1" />
</segment>
<segment time="22.3322673271962" length="0" sourcetrack="0"  >
	<beattype id="1" pattern="0" measure="0" beat="1" tatum="1" />
</segment>
<segment time="22.7182990732462" length="0" sourcetrack="0"  >
	<beattype id="1" pattern="0" measure="0" beat="1" tatum="1" />
</segment>
<segment time="23.1072333135962" length="0" sourcetrack="0"  >
	<beattype id="1" pattern="0" measure="0" beat="1" tatum="1" />
</segment>
<segment time="23.4961675539462" length="0" sourcetrack="0"  >
	<beattype id="1" pattern="0" measure="1" beat="1" tatum="1" />
</segment>
<segment time="23.8821992999962" length="0" sourcetrack="0"  >
	<beattype id="1" pattern="0" measure="0" beat="1" tatum="1" />
</segment>
<segment time="24.1385936737061" length="0" sourcetrack="0"  >
	<beattype id="1" pattern="0" measure="0" beat="0" tatum="1" />
</segment>
<segment time="24.2682310460462" length="0" sourcetrack="0"  >
	<beattype id="1" pattern="0" measure="0" beat="1" tatum="1" />
</segment>
<segment time="24.6600677806962" length="0" sourcetrack="0"  >
	<beattype id="1" pattern="0" measure="0" beat="1" tatum="1" />
</segment>
<segment time="25.0519045153462" length="0" sourcetrack="0"  >
	<beattype id="1" pattern="0" measure="1" beat="1" tatum="1" />
</segment>
<segment time="25.2991828918457" length="0" sourcetrack="0"  >
	<beattype id="1" pattern="0" measure="0" beat="0" tatum="1" />
</segment>
<segment time="25.4445309192942" length="0" sourcetrack="0"  >
	<beattype id="1" pattern="0" measure="0" beat="1" tatum="1" />
</segment>
<segment time="25.8371573232421" length="0" sourcetrack="0"  >
	<beattype id="1" pattern="0" measure="0" beat="1" tatum="1" />
</segment>
<segment time="26.0766448974609" length="0" sourcetrack="0"  >
	<beattype id="1" pattern="0" measure="0" beat="0" tatum="1" />
</segment>
<segment time="26.2229954734059" length="0" sourcetrack="0"  >
	<beattype id="1" pattern="0" measure="0" beat="1" tatum="1" />
</segment>
<segment time="26.4471664428711" length="0" sourcetrack="0"  >
	<beattype id="1" pattern="0" measure="0" beat="0" tatum="1" />
</segment>
<segment time="26.6088336235697" length="0" sourcetrack="0"  >
	<beattype id="1" pattern="0" measure="1" beat="1" tatum="1" />
</segment>
<segment time="26.9926595208759" length="0" sourcetrack="0"  >
	<beattype id="1" pattern="0" measure="0" beat="1" tatum="1" />
</segment>
<segment time="27.376485418182" length="0" sourcetrack="0"  >
	<beattype id="1" pattern="0" measure="0" beat="1" tatum="1" />
</segment>
<segment time="27.7554194565641" length="0" sourcetrack="0"  >
	<beattype id="1" pattern="0" measure="0" beat="1" tatum="1" />
</segment>
<segment time="28.1343534949462" length="0" sourcetrack="0"  >
	<beattype id="1" pattern="0" measure="1" beat="1" tatum="1" />
</segment>
<segment time="28.522979725406" length="0" sourcetrack="0"  >
	<beattype id="1" pattern="0" measure="0" beat="1" tatum="1" />
</segment>
<segment time="28.9116059558658" length="0" sourcetrack="0"  >
	<beattype id="1" pattern="0" measure="0" beat="1" tatum="1" />
</segment>
<segment time="29.2984712132683" length="0" sourcetrack="0"  >
	<beattype id="1" pattern="0" measure="0" beat="1" tatum="1" />
</segment>
<segment time="29.6853364706709" length="0" sourcetrack="0"  >
	<beattype id="1" pattern="0" measure="1" beat="1" tatum="1" />
</segment>
</musicdescription>
