<?xml version="1.0" encoding="UTF-8" standalone="yes" ?>
<musicdescription xmlns="http://www.ircam.fr/musicdescription/1.1" xmlns:xsi="http://www.w3.org/2001/XMLSchema-instance" xsi:schemaLocation="http://www.ircam.fr/musicdescription/1.1 http://recherche.ircam.fr/anasyn/xsd/musicdescription_1.1.xsd" format="20140305A" date="2015-10-28" >
<media>./reggae/reggae.00096.wav</media>
<descriptiondefinition id="1" >
	<type>beattype</type>
	<generator name="AudioSculpt" version="3.3.9" date="2015-10-28" />
</descriptiondefinition>
<segment time="0.213222727179527" length="0" sourcetrack="0"  >
	<beattype id="1" pattern="0" measure="0" beat="1" tatum="1" />
</segment>
<segment time="0.537253260612488" length="0" sourcetrack="0"  >
	<beattype id="1" pattern="0" measure="1" beat="1" tatum="1" />
</segment>
<segment time="0.885552583776351" length="0" sourcetrack="0"  >
	<beattype id="1" pattern="0" measure="0" beat="1" tatum="1" />
</segment>
<segment time="1.23385190352635" length="0" sourcetrack="0"  >
	<beattype id="1" pattern="0" measure="0" beat="1" tatum="1" />
</segment>
<segment time="1.57054124592635" length="0" sourcetrack="0"  >
	<beattype id="1" pattern="0" measure="0" beat="1" tatum="1" />
</segment>
<segment time="1.90723061561584" length="0" sourcetrack="0"  >
	<beattype id="1" pattern="0" measure="1" beat="1" tatum="1" />
</segment>
<segment time="2.24101743637635" length="0" sourcetrack="0"  >
	<beattype id="1" pattern="0" measure="0" beat="1" tatum="1" />
</segment>
<segment time="2.57480428442635" length="0" sourcetrack="0"  >
	<beattype id="1" pattern="0" measure="0" beat="1" tatum="1" />
</segment>
<segment time="2.91729861552635" length="0" sourcetrack="0"  >
	<beattype id="1" pattern="0" measure="0" beat="1" tatum="1" />
</segment>
<segment time="3.25979294662635" length="0" sourcetrack="0"  >
	<beattype id="1" pattern="0" measure="1" beat="1" tatum="1" />
</segment>
<segment time="3.59015440803643" length="0" sourcetrack="0"  >
	<beattype id="1" pattern="0" measure="0" beat="1" tatum="1" />
</segment>
<segment time="3.92051586944652" length="0" sourcetrack="0"  >
	<beattype id="1" pattern="0" measure="0" beat="1" tatum="1" />
</segment>
<segment time="4.26010770619652" length="0" sourcetrack="0"  >
	<beattype id="1" pattern="0" measure="0" beat="1" tatum="1" />
</segment>
<segment time="4.59969954294652" length="0" sourcetrack="0"  >
	<beattype id="1" pattern="0" measure="1" beat="1" tatum="1" />
</segment>
<segment time="4.93929137969652" length="0" sourcetrack="0"  >
	<beattype id="1" pattern="0" measure="0" beat="1" tatum="1" />
</segment>
<segment time="5.27888321644652" length="0" sourcetrack="0"  >
	<beattype id="1" pattern="0" measure="0" beat="1" tatum="1" />
</segment>
<segment time="5.62119493234691" length="0" sourcetrack="0"  >
	<beattype id="1" pattern="0" measure="0" beat="1" tatum="1" />
</segment>
<segment time="5.9635066482473" length="0" sourcetrack="0"  >
	<beattype id="1" pattern="0" measure="1" beat="1" tatum="1" />
</segment>
<segment time="6.3030984849473" length="0" sourcetrack="0"  >
	<beattype id="1" pattern="0" measure="0" beat="1" tatum="1" />
</segment>
<segment time="6.6426903216473" length="0" sourcetrack="0"  >
	<beattype id="1" pattern="0" measure="0" beat="1" tatum="1" />
</segment>
<segment time="6.9822821583973" length="0" sourcetrack="0"  >
	<beattype id="1" pattern="0" measure="0" beat="1" tatum="1" />
</segment>
<segment time="7.3218739951473" length="0" sourcetrack="0"  >
	<beattype id="1" pattern="0" measure="1" beat="1" tatum="1" />
</segment>
<segment time="7.66507383368682" length="0" sourcetrack="0"  >
	<beattype id="1" pattern="0" measure="0" beat="1" tatum="1" />
</segment>
<segment time="8.00827367222635" length="0" sourcetrack="0"  >
	<beattype id="1" pattern="0" measure="0" beat="1" tatum="1" />
</segment>
<segment time="8.34786550897635" length="0" sourcetrack="0"  >
	<beattype id="1" pattern="0" measure="0" beat="1" tatum="1" />
</segment>
<segment time="8.68745734572635" length="0" sourcetrack="0"  >
	<beattype id="1" pattern="0" measure="1" beat="1" tatum="1" />
</segment>
<segment time="9.02124419377635" length="0" sourcetrack="0"  >
	<beattype id="1" pattern="0" measure="0" beat="1" tatum="1" />
</segment>
<segment time="9.35503104182635" length="0" sourcetrack="0"  >
	<beattype id="1" pattern="0" measure="0" beat="1" tatum="1" />
</segment>
<segment time="9.69172038422638" length="0" sourcetrack="0"  >
	<beattype id="1" pattern="0" measure="0" beat="1" tatum="1" />
</segment>
<segment time="10.0284097266264" length="0" sourcetrack="0"  >
	<beattype id="1" pattern="0" measure="1" beat="1" tatum="1" />
</segment>
<segment time="10.3650990690264" length="0" sourcetrack="0"  >
	<beattype id="1" pattern="0" measure="0" beat="1" tatum="1" />
</segment>
<segment time="10.7017884114264" length="0" sourcetrack="0"  >
	<beattype id="1" pattern="0" measure="0" beat="1" tatum="1" />
</segment>
<segment time="11.0384777538264" length="0" sourcetrack="0"  >
	<beattype id="1" pattern="0" measure="0" beat="1" tatum="1" />
</segment>
<segment time="11.3751670962264" length="0" sourcetrack="0"  >
	<beattype id="1" pattern="0" measure="1" beat="1" tatum="1" />
</segment>
<segment time="11.7118564386264" length="0" sourcetrack="0"  >
	<beattype id="1" pattern="0" measure="0" beat="1" tatum="1" />
</segment>
<segment time="12.0485457810264" length="0" sourcetrack="0"  >
	<beattype id="1" pattern="0" measure="0" beat="1" tatum="1" />
</segment>
<segment time="12.3823326291264" length="0" sourcetrack="0"  >
	<beattype id="1" pattern="0" measure="0" beat="1" tatum="1" />
</segment>
<segment time="12.7161194772264" length="0" sourcetrack="0"  >
	<beattype id="1" pattern="0" measure="1" beat="1" tatum="1" />
</segment>
<segment time="13.0528088196264" length="0" sourcetrack="0"  >
	<beattype id="1" pattern="0" measure="0" beat="1" tatum="1" />
</segment>
<segment time="13.3894981620264" length="0" sourcetrack="0"  >
	<beattype id="1" pattern="0" measure="0" beat="1" tatum="1" />
</segment>
<segment time="13.7232850100764" length="0" sourcetrack="0"  >
	<beattype id="1" pattern="0" measure="0" beat="1" tatum="1" />
</segment>
<segment time="14.0570718581264" length="0" sourcetrack="0"  >
	<beattype id="1" pattern="0" measure="1" beat="1" tatum="1" />
</segment>
<segment time="14.3966636948764" length="0" sourcetrack="0"  >
	<beattype id="1" pattern="0" measure="0" beat="1" tatum="1" />
</segment>
<segment time="14.7362555316264" length="0" sourcetrack="0"  >
	<beattype id="1" pattern="0" measure="0" beat="1" tatum="1" />
</segment>
<segment time="15.0729448740264" length="0" sourcetrack="0"  >
	<beattype id="1" pattern="0" measure="0" beat="1" tatum="1" />
</segment>
<segment time="15.4096342164264" length="0" sourcetrack="0"  >
	<beattype id="1" pattern="0" measure="1" beat="1" tatum="1" />
</segment>
<segment time="15.7463235588264" length="0" sourcetrack="0"  >
	<beattype id="1" pattern="0" measure="0" beat="1" tatum="1" />
</segment>
<segment time="16.0830129012264" length="0" sourcetrack="0"  >
	<beattype id="1" pattern="0" measure="0" beat="1" tatum="1" />
</segment>
<segment time="16.4197022436264" length="0" sourcetrack="0"  >
	<beattype id="1" pattern="0" measure="0" beat="1" tatum="1" />
</segment>
<segment time="16.7563915860264" length="0" sourcetrack="0"  >
	<beattype id="1" pattern="0" measure="1" beat="1" tatum="1" />
</segment>
<segment time="17.0901784341264" length="0" sourcetrack="0"  >
	<beattype id="1" pattern="0" measure="0" beat="1" tatum="1" />
</segment>
<segment time="17.4239652822264" length="0" sourcetrack="0"  >
	<beattype id="1" pattern="0" measure="0" beat="1" tatum="1" />
</segment>
<segment time="17.7606546246264" length="0" sourcetrack="0"  >
	<beattype id="1" pattern="0" measure="0" beat="1" tatum="1" />
</segment>
<segment time="18.0973439670264" length="0" sourcetrack="0"  >
	<beattype id="1" pattern="0" measure="1" beat="1" tatum="1" />
</segment>
<segment time="18.4340333094264" length="0" sourcetrack="0"  >
	<beattype id="1" pattern="0" measure="0" beat="1" tatum="1" />
</segment>
<segment time="18.7707226518264" length="0" sourcetrack="0"  >
	<beattype id="1" pattern="0" measure="0" beat="1" tatum="1" />
</segment>
<segment time="19.1074119942264" length="0" sourcetrack="0"  >
	<beattype id="1" pattern="0" measure="0" beat="1" tatum="1" />
</segment>
<segment time="19.4441013366264" length="0" sourcetrack="0"  >
	<beattype id="1" pattern="0" measure="1" beat="1" tatum="1" />
</segment>
<segment time="19.7778881846764" length="0" sourcetrack="0"  >
	<beattype id="1" pattern="0" measure="0" beat="1" tatum="1" />
</segment>
<segment time="20.1116750327264" length="0" sourcetrack="0"  >
	<beattype id="1" pattern="0" measure="0" beat="1" tatum="1" />
</segment>
<segment time="20.4483643751264" length="0" sourcetrack="0"  >
	<beattype id="1" pattern="0" measure="0" beat="1" tatum="1" />
</segment>
<segment time="20.7850537175264" length="0" sourcetrack="0"  >
	<beattype id="1" pattern="0" measure="1" beat="1" tatum="1" />
</segment>
<segment time="21.1188405656264" length="0" sourcetrack="0"  >
	<beattype id="1" pattern="0" measure="0" beat="1" tatum="1" />
</segment>
<segment time="21.4526274137264" length="0" sourcetrack="0"  >
	<beattype id="1" pattern="0" measure="0" beat="1" tatum="1" />
</segment>
<segment time="21.7893167561264" length="0" sourcetrack="0"  >
	<beattype id="1" pattern="0" measure="0" beat="1" tatum="1" />
</segment>
<segment time="22.1260060985264" length="0" sourcetrack="0"  >
	<beattype id="1" pattern="0" measure="1" beat="1" tatum="1" />
</segment>
<segment time="22.4626954409264" length="0" sourcetrack="0"  >
	<beattype id="1" pattern="0" measure="0" beat="1" tatum="1" />
</segment>
<segment time="22.7993847833264" length="0" sourcetrack="0"  >
	<beattype id="1" pattern="0" measure="0" beat="1" tatum="1" />
</segment>
<segment time="23.1389766200764" length="0" sourcetrack="0"  >
	<beattype id="1" pattern="0" measure="0" beat="1" tatum="1" />
</segment>
<segment time="23.4785684568264" length="0" sourcetrack="0"  >
	<beattype id="1" pattern="0" measure="1" beat="1" tatum="1" />
</segment>
<segment time="23.8152577992264" length="0" sourcetrack="0"  >
	<beattype id="1" pattern="0" measure="0" beat="1" tatum="1" />
</segment>
<segment time="24.1519471416264" length="0" sourcetrack="0"  >
	<beattype id="1" pattern="0" measure="0" beat="1" tatum="1" />
</segment>
<segment time="24.4886364840264" length="0" sourcetrack="0"  >
	<beattype id="1" pattern="0" measure="0" beat="1" tatum="1" />
</segment>
<segment time="24.8253258264264" length="0" sourcetrack="0"  >
	<beattype id="1" pattern="0" measure="1" beat="1" tatum="1" />
</segment>
<segment time="25.1620151688264" length="0" sourcetrack="0"  >
	<beattype id="1" pattern="0" measure="0" beat="1" tatum="1" />
</segment>
<segment time="25.4987045112264" length="0" sourcetrack="0"  >
	<beattype id="1" pattern="0" measure="0" beat="1" tatum="1" />
</segment>
<segment time="25.8353938536264" length="0" sourcetrack="0"  >
	<beattype id="1" pattern="0" measure="0" beat="1" tatum="1" />
</segment>
<segment time="26.1720831960264" length="0" sourcetrack="0"  >
	<beattype id="1" pattern="0" measure="1" beat="1" tatum="1" />
</segment>
<segment time="26.5087725384264" length="0" sourcetrack="0"  >
	<beattype id="1" pattern="0" measure="0" beat="1" tatum="1" />
</segment>
<segment time="26.8454618808264" length="0" sourcetrack="0"  >
	<beattype id="1" pattern="0" measure="0" beat="1" tatum="1" />
</segment>
<segment time="27.1850537175764" length="0" sourcetrack="0"  >
	<beattype id="1" pattern="0" measure="0" beat="1" tatum="1" />
</segment>
<segment time="27.5246455543264" length="0" sourcetrack="0"  >
	<beattype id="1" pattern="0" measure="1" beat="1" tatum="1" />
</segment>
<segment time="27.8613348967264" length="0" sourcetrack="0"  >
	<beattype id="1" pattern="0" measure="0" beat="1" tatum="1" />
</segment>
<segment time="28.1980242391264" length="0" sourcetrack="0"  >
	<beattype id="1" pattern="0" measure="0" beat="1" tatum="1" />
</segment>
<segment time="28.5347135815264" length="0" sourcetrack="0"  >
	<beattype id="1" pattern="0" measure="0" beat="1" tatum="1" />
</segment>
<segment time="28.8714029239264" length="0" sourcetrack="0"  >
	<beattype id="1" pattern="0" measure="1" beat="1" tatum="1" />
</segment>
<segment time="29.2051897719764" length="0" sourcetrack="0"  >
	<beattype id="1" pattern="0" measure="0" beat="1" tatum="1" />
</segment>
<segment time="29.5389766200264" length="0" sourcetrack="0"  >
	<beattype id="1" pattern="0" measure="0" beat="1" tatum="1" />
</segment>
<segment time="29.8438091278076" length="0" sourcetrack="0"  >
	<beattype id="1" pattern="0" measure="0" beat="1" tatum="1" />
</segment>
</musicdescription>
