<?xml version="1.0" encoding="UTF-8" standalone="yes" ?>
<musicdescription xmlns="http://www.ircam.fr/musicdescription/1.1" xmlns:xsi="http://www.w3.org/2001/XMLSchema-instance" xsi:schemaLocation="http://www.ircam.fr/musicdescription/1.1 http://recherche.ircam.fr/anasyn/xsd/musicdescription_1.1.xsd" format="20140305A" date="2015-10-28" >
<media>./reggae/reggae.00034.wav</media>
<descriptiondefinition id="1" >
	<type>beattype</type>
	<generator name="AudioSculpt" version="3.3.9" date="2015-10-28" />
</descriptiondefinition>
<segment time="0.216054424643517" length="0" sourcetrack="0"  >
	<beattype id="1" pattern="0" measure="0" beat="1" tatum="1" />
</segment>
<segment time="0.561688005924225" length="0" sourcetrack="0"  >
	<beattype id="1" pattern="0" measure="1" beat="1" tatum="1" />
</segment>
<segment time="0.880962371826172" length="0" sourcetrack="0"  >
	<beattype id="1" pattern="0" measure="0" beat="1" tatum="1" />
</segment>
<segment time="1.20023667812347" length="0" sourcetrack="0"  >
	<beattype id="1" pattern="0" measure="0" beat="1" tatum="1" />
</segment>
<segment time="1.51951110363007" length="0" sourcetrack="0"  >
	<beattype id="1" pattern="0" measure="0" beat="1" tatum="1" />
</segment>
<segment time="1.83878552913666" length="0" sourcetrack="0"  >
	<beattype id="1" pattern="0" measure="1" beat="1" tatum="1" />
</segment>
<segment time="2.16096234321594" length="0" sourcetrack="0"  >
	<beattype id="1" pattern="0" measure="0" beat="1" tatum="1" />
</segment>
<segment time="2.48313927650452" length="0" sourcetrack="0"  >
	<beattype id="1" pattern="0" measure="0" beat="1" tatum="1" />
</segment>
<segment time="2.80241370201111" length="0" sourcetrack="0"  >
	<beattype id="1" pattern="0" measure="0" beat="1" tatum="1" />
</segment>
<segment time="3.12168788909912" length="0" sourcetrack="0"  >
	<beattype id="1" pattern="0" measure="1" beat="1" tatum="1" />
</segment>
<segment time="3.44096231460571" length="0" sourcetrack="0"  >
	<beattype id="1" pattern="0" measure="0" beat="1" tatum="1" />
</segment>
<segment time="3.7602367401123" length="0" sourcetrack="0"  >
	<beattype id="1" pattern="0" measure="0" beat="1" tatum="1" />
</segment>
<segment time="4.08241367340088" length="0" sourcetrack="0"  >
	<beattype id="1" pattern="0" measure="0" beat="1" tatum="1" />
</segment>
<segment time="4.40459060668945" length="0" sourcetrack="0"  >
	<beattype id="1" pattern="0" measure="1" beat="1" tatum="1" />
</segment>
<segment time="4.72096252441406" length="0" sourcetrack="0"  >
	<beattype id="1" pattern="0" measure="0" beat="1" tatum="1" />
</segment>
<segment time="5.03733444213867" length="0" sourcetrack="0"  >
	<beattype id="1" pattern="0" measure="0" beat="1" tatum="1" />
</segment>
<segment time="5.35951089859009" length="0" sourcetrack="0"  >
	<beattype id="1" pattern="0" measure="0" beat="1" tatum="1" />
</segment>
<segment time="5.68168783187866" length="0" sourcetrack="0"  >
	<beattype id="1" pattern="0" measure="1" beat="1" tatum="1" />
</segment>
<segment time="6.00096225738525" length="0" sourcetrack="0"  >
	<beattype id="1" pattern="0" measure="0" beat="1" tatum="1" />
</segment>
<segment time="6.32023668289185" length="0" sourcetrack="0"  >
	<beattype id="1" pattern="0" measure="0" beat="1" tatum="1" />
</segment>
<segment time="6.63951110839844" length="0" sourcetrack="0"  >
	<beattype id="1" pattern="0" measure="0" beat="1" tatum="1" />
</segment>
<segment time="6.95878553390503" length="0" sourcetrack="0"  >
	<beattype id="1" pattern="0" measure="1" beat="1" tatum="1" />
</segment>
<segment time="7.2809624671936" length="0" sourcetrack="0"  >
	<beattype id="1" pattern="0" measure="0" beat="1" tatum="1" />
</segment>
<segment time="7.60313940048218" length="0" sourcetrack="0"  >
	<beattype id="1" pattern="0" measure="0" beat="1" tatum="1" />
</segment>
<segment time="7.92241382598877" length="0" sourcetrack="0"  >
	<beattype id="1" pattern="0" measure="0" beat="1" tatum="1" />
</segment>
<segment time="8.2416877746582" length="0" sourcetrack="0"  >
	<beattype id="1" pattern="0" measure="1" beat="1" tatum="1" />
</segment>
<segment time="8.56096267700195" length="0" sourcetrack="0"  >
	<beattype id="1" pattern="0" measure="0" beat="1" tatum="1" />
</segment>
<segment time="8.88023662567139" length="0" sourcetrack="0"  >
	<beattype id="1" pattern="0" measure="0" beat="1" tatum="1" />
</segment>
<segment time="9.19951152801514" length="0" sourcetrack="0"  >
	<beattype id="1" pattern="0" measure="0" beat="1" tatum="1" />
</segment>
<segment time="9.51878547668457" length="0" sourcetrack="0"  >
	<beattype id="1" pattern="0" measure="1" beat="1" tatum="1" />
</segment>
<segment time="9.838059425354" length="0" sourcetrack="0"  >
	<beattype id="1" pattern="0" measure="0" beat="1" tatum="1" />
</segment>
<segment time="10.1573343276978" length="0" sourcetrack="0"  >
	<beattype id="1" pattern="0" measure="0" beat="1" tatum="1" />
</segment>
<segment time="10.4737062454224" length="0" sourcetrack="0"  >
	<beattype id="1" pattern="0" measure="0" beat="1" tatum="1" />
</segment>
<segment time="10.790078163147" length="0" sourcetrack="0"  >
	<beattype id="1" pattern="0" measure="1" beat="1" tatum="1" />
</segment>
<segment time="11.1093521118164" length="0" sourcetrack="0"  >
	<beattype id="1" pattern="0" measure="0" beat="1" tatum="1" />
</segment>
<segment time="11.4286270141602" length="0" sourcetrack="0"  >
	<beattype id="1" pattern="0" measure="0" beat="1" tatum="1" />
</segment>
<segment time="11.7479009628296" length="0" sourcetrack="0"  >
	<beattype id="1" pattern="0" measure="0" beat="1" tatum="1" />
</segment>
<segment time="12.0671758651733" length="0" sourcetrack="0"  >
	<beattype id="1" pattern="0" measure="1" beat="1" tatum="1" />
</segment>
<segment time="12.3835477828979" length="0" sourcetrack="0"  >
	<beattype id="1" pattern="0" measure="0" beat="1" tatum="1" />
</segment>
<segment time="12.6999197006226" length="0" sourcetrack="0"  >
	<beattype id="1" pattern="0" measure="0" beat="1" tatum="1" />
</segment>
<segment time="13.019193649292" length="0" sourcetrack="0"  >
	<beattype id="1" pattern="0" measure="0" beat="1" tatum="1" />
</segment>
<segment time="13.3384675979614" length="0" sourcetrack="0"  >
	<beattype id="1" pattern="0" measure="1" beat="1" tatum="1" />
</segment>
<segment time="13.654839515686" length="0" sourcetrack="0"  >
	<beattype id="1" pattern="0" measure="0" beat="1" tatum="1" />
</segment>
<segment time="13.9712114334106" length="0" sourcetrack="0"  >
	<beattype id="1" pattern="0" measure="0" beat="1" tatum="1" />
</segment>
<segment time="14.2904863357544" length="0" sourcetrack="0"  >
	<beattype id="1" pattern="0" measure="0" beat="1" tatum="1" />
</segment>
<segment time="14.6097602844238" length="0" sourcetrack="0"  >
	<beattype id="1" pattern="0" measure="1" beat="1" tatum="1" />
</segment>
<segment time="14.9261322021484" length="0" sourcetrack="0"  >
	<beattype id="1" pattern="0" measure="0" beat="1" tatum="1" />
</segment>
<segment time="15.242504119873" length="0" sourcetrack="0"  >
	<beattype id="1" pattern="0" measure="0" beat="1" tatum="1" />
</segment>
<segment time="15.5588760375977" length="0" sourcetrack="0"  >
	<beattype id="1" pattern="0" measure="0" beat="1" tatum="1" />
</segment>
<segment time="15.8752479553223" length="0" sourcetrack="0"  >
	<beattype id="1" pattern="0" measure="1" beat="1" tatum="1" />
</segment>
<segment time="16.2032299041748" length="0" sourcetrack="0"  >
	<beattype id="1" pattern="0" measure="0" beat="1" tatum="1" />
</segment>
<segment time="16.5184669494629" length="0" sourcetrack="0"  >
	<beattype id="1" pattern="0" measure="0" beat="1" tatum="1" />
</segment>
<segment time="16.8387145996094" length="0" sourcetrack="0"  >
	<beattype id="1" pattern="0" measure="0" beat="1" tatum="1" />
</segment>
<segment time="17.1634922027588" length="0" sourcetrack="0"  >
	<beattype id="1" pattern="0" measure="1" beat="1" tatum="1" />
</segment>
<segment time="17.4654846191406" length="0" sourcetrack="0"  >
	<beattype id="1" pattern="0" measure="0" beat="1" tatum="1" />
</segment>
<segment time="17.7903060913086" length="0" sourcetrack="0"  >
	<beattype id="1" pattern="0" measure="0" beat="1" tatum="1" />
</segment>
<segment time="18.0985584259033" length="0" sourcetrack="0"  >
	<beattype id="1" pattern="0" measure="0" beat="1" tatum="1" />
</segment>
<segment time="18.4149303436279" length="0" sourcetrack="0"  >
	<beattype id="1" pattern="0" measure="1" beat="1" tatum="1" />
</segment>
<segment time="18.7313022613525" length="0" sourcetrack="0"  >
	<beattype id="1" pattern="0" measure="0" beat="1" tatum="1" />
</segment>
<segment time="19.0505771636963" length="0" sourcetrack="0"  >
	<beattype id="1" pattern="0" measure="0" beat="1" tatum="1" />
</segment>
<segment time="19.36985206604" length="0" sourcetrack="0"  >
	<beattype id="1" pattern="0" measure="0" beat="1" tatum="1" />
</segment>
<segment time="19.6862239837646" length="0" sourcetrack="0"  >
	<beattype id="1" pattern="0" measure="1" beat="1" tatum="1" />
</segment>
<segment time="20.0025959014893" length="0" sourcetrack="0"  >
	<beattype id="1" pattern="0" measure="0" beat="1" tatum="1" />
</segment>
<segment time="20.3247718811035" length="0" sourcetrack="0"  >
	<beattype id="1" pattern="0" measure="0" beat="1" tatum="1" />
</segment>
<segment time="20.6469478607178" length="0" sourcetrack="0"  >
	<beattype id="1" pattern="0" measure="0" beat="1" tatum="1" />
</segment>
<segment time="20.9633197784424" length="0" sourcetrack="0"  >
	<beattype id="1" pattern="0" measure="1" beat="1" tatum="1" />
</segment>
<segment time="21.279691696167" length="0" sourcetrack="0"  >
	<beattype id="1" pattern="0" measure="0" beat="1" tatum="1" />
</segment>
<segment time="21.5960636138916" length="0" sourcetrack="0"  >
	<beattype id="1" pattern="0" measure="0" beat="1" tatum="1" />
</segment>
<segment time="21.9124355316162" length="0" sourcetrack="0"  >
	<beattype id="1" pattern="0" measure="0" beat="1" tatum="1" />
</segment>
<segment time="22.23171043396" length="0" sourcetrack="0"  >
	<beattype id="1" pattern="0" measure="1" beat="1" tatum="1" />
</segment>
<segment time="22.5509853363037" length="0" sourcetrack="0"  >
	<beattype id="1" pattern="0" measure="0" beat="1" tatum="1" />
</segment>
<segment time="22.8702602386475" length="0" sourcetrack="0"  >
	<beattype id="1" pattern="0" measure="0" beat="1" tatum="1" />
</segment>
<segment time="23.1895332336426" length="0" sourcetrack="0"  >
	<beattype id="1" pattern="0" measure="0" beat="1" tatum="1" />
</segment>
<segment time="23.5059051513672" length="0" sourcetrack="0"  >
	<beattype id="1" pattern="0" measure="1" beat="1" tatum="1" />
</segment>
<segment time="23.8222770690918" length="0" sourcetrack="0"  >
	<beattype id="1" pattern="0" measure="0" beat="1" tatum="1" />
</segment>
<segment time="24.1415519714355" length="0" sourcetrack="0"  >
	<beattype id="1" pattern="0" measure="0" beat="1" tatum="1" />
</segment>
<segment time="24.4608268737793" length="0" sourcetrack="0"  >
	<beattype id="1" pattern="0" measure="0" beat="1" tatum="1" />
</segment>
<segment time="24.7800998687744" length="0" sourcetrack="0"  >
	<beattype id="1" pattern="0" measure="1" beat="1" tatum="1" />
</segment>
<segment time="25.0993747711182" length="0" sourcetrack="0"  >
	<beattype id="1" pattern="0" measure="0" beat="1" tatum="1" />
</segment>
<segment time="25.4157466888428" length="0" sourcetrack="0"  >
	<beattype id="1" pattern="0" measure="0" beat="1" tatum="1" />
</segment>
<segment time="25.7321186065674" length="0" sourcetrack="0"  >
	<beattype id="1" pattern="0" measure="0" beat="1" tatum="1" />
</segment>
<segment time="26.0513935089111" length="0" sourcetrack="0"  >
	<beattype id="1" pattern="0" measure="1" beat="1" tatum="1" />
</segment>
<segment time="26.3706684112549" length="0" sourcetrack="0"  >
	<beattype id="1" pattern="0" measure="0" beat="1" tatum="1" />
</segment>
<segment time="26.6870403289795" length="0" sourcetrack="0"  >
	<beattype id="1" pattern="0" measure="0" beat="1" tatum="1" />
</segment>
<segment time="27.0034122467041" length="0" sourcetrack="0"  >
	<beattype id="1" pattern="0" measure="0" beat="1" tatum="1" />
</segment>
<segment time="27.3226852416992" length="0" sourcetrack="0"  >
	<beattype id="1" pattern="0" measure="1" beat="1" tatum="1" />
</segment>
<segment time="27.641960144043" length="0" sourcetrack="0"  >
	<beattype id="1" pattern="0" measure="0" beat="1" tatum="1" />
</segment>
<segment time="27.9612350463867" length="0" sourcetrack="0"  >
	<beattype id="1" pattern="0" measure="0" beat="1" tatum="1" />
</segment>
<segment time="28.2805080413818" length="0" sourcetrack="0"  >
	<beattype id="1" pattern="0" measure="0" beat="1" tatum="1" />
</segment>
<segment time="28.5997829437256" length="0" sourcetrack="0"  >
	<beattype id="1" pattern="0" measure="1" beat="1" tatum="1" />
</segment>
<segment time="28.9190578460693" length="0" sourcetrack="0"  >
	<beattype id="1" pattern="0" measure="0" beat="1" tatum="1" />
</segment>
<segment time="29.2354297637939" length="0" sourcetrack="0"  >
	<beattype id="1" pattern="0" measure="0" beat="1" tatum="1" />
</segment>
<segment time="29.5518016815186" length="0" sourcetrack="0"  >
	<beattype id="1" pattern="0" measure="0" beat="1" tatum="1" />
</segment>
<segment time="29.865270614624" length="0" sourcetrack="0"  >
	<beattype id="1" pattern="0" measure="1" beat="1" tatum="1" />
</segment>
</musicdescription>
