<?xml version="1.0" encoding="UTF-8" standalone="yes" ?>
<musicdescription xmlns="http://www.ircam.fr/musicdescription/1.1" xmlns:xsi="http://www.w3.org/2001/XMLSchema-instance" xsi:schemaLocation="http://www.ircam.fr/musicdescription/1.1 http://recherche.ircam.fr/anasyn/xsd/musicdescription_1.1.xsd" format="20140305A" date="2015-10-28" >
<media>./rock/rock.00071.wav</media>
<descriptiondefinition id="1" >
	<type>beattype</type>
	<generator name="AudioSculpt" version="3.3.4" date="2015-10-28" />
</descriptiondefinition>
<segment time="0.1205088423" length="0" sourcetrack="0"  >
	<beattype id="1" pattern="0" measure="0" beat="1" tatum="1" />
</segment>
<segment time="0.6545677992" length="0" sourcetrack="0"  >
	<beattype id="1" pattern="0" measure="0" beat="1" tatum="1" />
</segment>
<segment time="1.1944317448" length="0" sourcetrack="0"  >
	<beattype id="1" pattern="0" measure="1" beat="1" tatum="1" />
</segment>
<segment time="1.7284907017" length="0" sourcetrack="0"  >
	<beattype id="1" pattern="0" measure="0" beat="1" tatum="1" />
</segment>
<segment time="2.2625496586" length="0" sourcetrack="0"  >
	<beattype id="1" pattern="0" measure="0" beat="1" tatum="1" />
</segment>
<segment time="2.7966086155" length="0" sourcetrack="0"  >
	<beattype id="1" pattern="0" measure="0" beat="1" tatum="1" />
</segment>
<segment time="3.3364725611" length="0" sourcetrack="0"  >
	<beattype id="1" pattern="0" measure="1" beat="1" tatum="1" />
</segment>
<segment time="3.870531518" length="0" sourcetrack="0"  >
	<beattype id="1" pattern="0" measure="0" beat="1" tatum="1" />
</segment>
<segment time="4.4045904749" length="0" sourcetrack="0"  >
	<beattype id="1" pattern="0" measure="0" beat="1" tatum="1" />
</segment>
<segment time="4.9386494318" length="0" sourcetrack="0"  >
	<beattype id="1" pattern="0" measure="0" beat="1" tatum="1" />
</segment>
<segment time="5.4785133774" length="0" sourcetrack="0"  >
	<beattype id="1" pattern="0" measure="1" beat="1" tatum="1" />
</segment>
<segment time="6.0125723343" length="0" sourcetrack="0"  >
	<beattype id="1" pattern="0" measure="0" beat="1" tatum="1" />
</segment>
<segment time="6.5466312912" length="0" sourcetrack="0"  >
	<beattype id="1" pattern="0" measure="0" beat="1" tatum="1" />
</segment>
<segment time="7.0806902482" length="0" sourcetrack="0"  >
	<beattype id="1" pattern="0" measure="0" beat="1" tatum="1" />
</segment>
<segment time="7.6147492051" length="0" sourcetrack="0"  >
	<beattype id="1" pattern="0" measure="1" beat="1" tatum="1" />
</segment>
<segment time="8.148808162" length="0" sourcetrack="0"  >
	<beattype id="1" pattern="0" measure="0" beat="1" tatum="1" />
</segment>
<segment time="8.6886721076" length="0" sourcetrack="0"  >
	<beattype id="1" pattern="0" measure="0" beat="1" tatum="1" />
</segment>
<segment time="9.2227310645" length="0" sourcetrack="0"  >
	<beattype id="1" pattern="0" measure="0" beat="1" tatum="1" />
</segment>
<segment time="9.7567900214" length="0" sourcetrack="0"  >
	<beattype id="1" pattern="0" measure="1" beat="1" tatum="1" />
</segment>
<segment time="10.296653967" length="0" sourcetrack="0"  >
	<beattype id="1" pattern="0" measure="0" beat="1" tatum="1" />
</segment>
<segment time="10.8307129239" length="0" sourcetrack="0"  >
	<beattype id="1" pattern="0" measure="0" beat="1" tatum="1" />
</segment>
<segment time="11.3647718808" length="0" sourcetrack="0"  >
	<beattype id="1" pattern="0" measure="0" beat="1" tatum="1" />
</segment>
<segment time="11.8988308377" length="0" sourcetrack="0"  >
	<beattype id="1" pattern="0" measure="1" beat="1" tatum="1" />
</segment>
<segment time="12.4328897946" length="0" sourcetrack="0"  >
	<beattype id="1" pattern="0" measure="0" beat="1" tatum="1" />
</segment>
<segment time="12.9669487516" length="0" sourcetrack="0"  >
	<beattype id="1" pattern="0" measure="0" beat="1" tatum="1" />
</segment>
<segment time="13.5010077085" length="0" sourcetrack="0"  >
	<beattype id="1" pattern="0" measure="0" beat="1" tatum="1" />
</segment>
<segment time="14.0350666654" length="0" sourcetrack="0"  >
	<beattype id="1" pattern="0" measure="1" beat="1" tatum="1" />
</segment>
<segment time="14.574930611" length="0" sourcetrack="0"  >
	<beattype id="1" pattern="0" measure="0" beat="1" tatum="1" />
</segment>
<segment time="15.1089895679" length="0" sourcetrack="0"  >
	<beattype id="1" pattern="0" measure="0" beat="1" tatum="1" />
</segment>
<segment time="15.6430485248" length="0" sourcetrack="0"  >
	<beattype id="1" pattern="0" measure="0" beat="1" tatum="1" />
</segment>
<segment time="16.1771074817" length="0" sourcetrack="0"  >
	<beattype id="1" pattern="0" measure="1" beat="1" tatum="1" />
</segment>
<segment time="16.7084017098928" length="0" sourcetrack="0"  >
	<beattype id="1" pattern="0" measure="0" beat="1" tatum="1" />
</segment>
<segment time="17.2510303842" length="0" sourcetrack="0"  >
	<beattype id="1" pattern="0" measure="0" beat="1" tatum="1" />
</segment>
<segment time="17.7850893411" length="0" sourcetrack="0"  >
	<beattype id="1" pattern="0" measure="0" beat="1" tatum="1" />
</segment>
<segment time="18.319148298" length="0" sourcetrack="0"  >
	<beattype id="1" pattern="0" measure="1" beat="1" tatum="1" />
</segment>
<segment time="18.853207255" length="0" sourcetrack="0"  >
	<beattype id="1" pattern="0" measure="0" beat="1" tatum="1" />
</segment>
<segment time="19.3872662119" length="0" sourcetrack="0"  >
	<beattype id="1" pattern="0" measure="0" beat="1" tatum="1" />
</segment>
<segment time="19.9213251688" length="0" sourcetrack="0"  >
	<beattype id="1" pattern="0" measure="0" beat="1" tatum="1" />
</segment>
<segment time="20.4611891144" length="0" sourcetrack="0"  >
	<beattype id="1" pattern="0" measure="1" beat="1" tatum="1" />
</segment>
<segment time="20.9952480713" length="0" sourcetrack="0"  >
	<beattype id="1" pattern="0" measure="0" beat="1" tatum="1" />
</segment>
<segment time="21.5293070282" length="0" sourcetrack="0"  >
	<beattype id="1" pattern="0" measure="0" beat="1" tatum="1" />
</segment>
<segment time="22.0633659851" length="0" sourcetrack="0"  >
	<beattype id="1" pattern="0" measure="0" beat="1" tatum="1" />
</segment>
<segment time="22.597424942" length="0" sourcetrack="0"  >
	<beattype id="1" pattern="0" measure="1" beat="1" tatum="1" />
</segment>
<segment time="23.1372888876" length="0" sourcetrack="0"  >
	<beattype id="1" pattern="0" measure="0" beat="1" tatum="1" />
</segment>
<segment time="23.6713478445" length="0" sourcetrack="0"  >
	<beattype id="1" pattern="0" measure="0" beat="1" tatum="1" />
</segment>
<segment time="24.2054068014" length="0" sourcetrack="0"  >
	<beattype id="1" pattern="0" measure="0" beat="1" tatum="1" />
</segment>
<segment time="24.7339220226348" length="0" sourcetrack="0"  >
	<beattype id="1" pattern="0" measure="1" beat="1" tatum="1" />
</segment>
<segment time="25.2793297039" length="0" sourcetrack="0"  >
	<beattype id="1" pattern="0" measure="0" beat="1" tatum="1" />
</segment>
<segment time="25.8061197552604" length="0" sourcetrack="0"  >
	<beattype id="1" pattern="0" measure="0" beat="1" tatum="1" />
</segment>
<segment time="26.3477727937779" length="0" sourcetrack="0"  >
	<beattype id="1" pattern="0" measure="0" beat="1" tatum="1" />
</segment>
<segment time="26.8838707064664" length="0" sourcetrack="0"  >
	<beattype id="1" pattern="0" measure="1" beat="1" tatum="1" />
</segment>
<segment time="27.4213705203" length="0" sourcetrack="0"  >
	<beattype id="1" pattern="0" measure="0" beat="1" tatum="1" />
</segment>
<segment time="27.9554294772" length="0" sourcetrack="0"  >
	<beattype id="1" pattern="0" measure="0" beat="1" tatum="1" />
</segment>
<segment time="28.4894884341" length="0" sourcetrack="0"  >
	<beattype id="1" pattern="0" measure="0" beat="1" tatum="1" />
</segment>
<segment time="29.023547391" length="0" sourcetrack="0"  >
	<beattype id="1" pattern="0" measure="1" beat="1" tatum="1" />
</segment>
<segment time="29.5518013593" length="0" sourcetrack="0"  >
	<beattype id="1" pattern="0" measure="0" beat="1" tatum="1" />
</segment>
</musicdescription>
